tgt/__init__.py
tgt/agreement.py
tgt/core.py
tgt/io.py
tgt/io3.py
tgt/util.py
tgt-1.5.data/scripts/tgt-concatenate-textgrids.py
tgt-1.5.data/scripts/tgt-extract-part.py
tgt-1.5.data/scripts/tgt-print-tiernames.py
tgt-1.5.data/scripts/tgt-shift-boundaries.py
tgt-1.5.dist-info/LICENSE
tgt-1.5.dist-info/METADATA
tgt-1.5.dist-info/WHEEL
tgt-1.5.dist-info/top_level.txt
tgt-1.5.dist-info/RECORD
